sensai/__init__.py
sensai/catboost.py
sensai/columngen.py
sensai/distance_metric.py
sensai/feature_importance.py
sensai/hyperopt.py
sensai/lightgbm.py
sensai/local_search.py
sensai/minizinc.py
sensai/multi_model.py
sensai/naive_bayes.py
sensai/nearest_neighbors.py
sensai/normalisation.py
sensai/sklearn_quantile.py
sensai/tensor_model.py
sensai/vector_model.py
sensai/vectoriser.py
sensai/xgboost.py
sensai/clustering/__init__.py
sensai/clustering/clustering_base.py
sensai/clustering/greedy_clustering.py
sensai/clustering/sklearn_clustering.py
sensai/data/__init__.py
sensai/data/dataset.py
sensai/data/io_data.py
sensai/data_transformation/__init__.py
sensai/data_transformation/dft.py
sensai/data_transformation/sklearn_transformer.py
sensai/data_transformation/value_transformation.py
sensai/ensemble/__init__.py
sensai/ensemble/ensemble_base.py
sensai/ensemble/models.py
sensai/evaluation/__init__.py
sensai/evaluation/crossval.py
sensai/evaluation/eval_util.py
sensai/evaluation/evaluator.py
sensai/evaluation/evaluator_clustering.py
sensai/evaluation/metric_computation.py
sensai/evaluation/result_set.py
sensai/evaluation/eval_stats/__init__.py
sensai/evaluation/eval_stats/eval_stats_base.py
sensai/evaluation/eval_stats/eval_stats_classification.py
sensai/evaluation/eval_stats/eval_stats_clustering.py
sensai/evaluation/eval_stats/eval_stats_regression.py
sensai/feature_selection/rfe.py
sensai/featuregen/__init__.py
sensai/featuregen/feature_generator.py
sensai/featuregen/feature_generator_registry.py
sensai/geoanalytics/__init__.py
sensai/geoanalytics/_globalmaptiles.py
sensai/geoanalytics/geo_clustering.py
sensai/geoanalytics/geo_coords.py
sensai/geoanalytics/local_coords.py
sensai/geoanalytics/map_tiles.py
sensai/geoanalytics/geopandas/__init__.py
sensai/geoanalytics/geopandas/coordinate_clustering.py
sensai/geoanalytics/geopandas/coordinate_clustering_ground_truth.py
sensai/geoanalytics/geopandas/coordinates.py
sensai/geoanalytics/geopandas/geometry.py
sensai-1.6.0.dist-info/licenses/LICENSE
sensai-1.6.0.dist-info/METADATA
sensai-1.6.0.dist-info/WHEEL
sensai-1.6.0.dist-info/dependency_links.txt
sensai-1.6.0.dist-info/top_level.txt
sensai-1.6.0.dist-info/RECORD
